Metadata-Version: 2.1
Name: flake8-Inflammatory-Jargon
Version: 1.0.1
Summary: replace Inflammatory words like blacklist and slave with more appropriate words
Home-page: UNKNOWN
Author: tomgold182
Author-email: tomgold182@gmail.com
License: MIT
Download-URL: https://github.com/tomgold182/flake8-Inflammatory-jargon/archive/v1.0.1.tar.gz
Keywords: linter,flake8,bad,jargon,slave,extension,Inflammatory
Platform: UNKNOWN
Classifier: Development Status :: 3 - Alpha
Classifier: Intended Audience :: Developers
Classifier: Natural Language :: English
Classifier: License :: OSI Approved :: MIT License
Classifier: Programming Language :: Python
Classifier: Programming Language :: Python :: 3.6
Classifier: Programming Language :: Python :: 3.7
Classifier: Programming Language :: Python :: 3.8
Requires-Python: >=3.6
Provides-Extra: dev
